<?xml version='1.0' encoding='UTF-8'?><!DOCTYPE paula SYSTEM "paula_feat.dtd">
<paula version="1.1">
	<header paula_id="GUM_academic_exposure.tok_PronType"/>
	<featList xmlns:xlink="http://www.w3.org/1999/xlink" type="PronType" xml:base="GUM_academic_exposure.tok.xml">
		<feat xlink:href="#sTok15" value="Art"/>
		<feat xlink:href="#sTok19" value="Art"/>
		<feat xlink:href="#sTok36" value="Dem"/>
		<feat xlink:href="#sTok43" value="Art"/>
		<feat xlink:href="#sTok71" value="Prs"/>
		<feat xlink:href="#sTok84" value="Prs"/>
		<feat xlink:href="#sTok90" value="Prs"/>
		<feat xlink:href="#sTok94" value="Art"/>
		<feat xlink:href="#sTok102" value="Art"/>
		<feat xlink:href="#sTok131" value="Art"/>
		<feat xlink:href="#sTok138" value="Art"/>
		<feat xlink:href="#sTok148" value="Int"/>
		<feat xlink:href="#sTok151" value="Art"/>
		<feat xlink:href="#sTok154" value="Art"/>
		<feat xlink:href="#sTok157" value="Dem"/>
		<feat xlink:href="#sTok169" value="Int"/>
		<feat xlink:href="#sTok174" value="Art"/>
		<feat xlink:href="#sTok179" value="Dem"/>
		<feat xlink:href="#sTok187" value="Art"/>
		<feat xlink:href="#sTok191" value="Prs"/>
		<feat xlink:href="#sTok193" value="Art"/>
		<feat xlink:href="#sTok197" value="Art"/>
		<feat xlink:href="#sTok203" value="Art"/>
		<feat xlink:href="#sTok209" value="Dem"/>
		<feat xlink:href="#sTok213" value="Art"/>
		<feat xlink:href="#sTok233" value="Prs"/>
		<feat xlink:href="#sTok236" value="Prs"/>
		<feat xlink:href="#sTok265" value="Prs"/>
		<feat xlink:href="#sTok274" value="Art"/>
		<feat xlink:href="#sTok277" value="Art"/>
		<feat xlink:href="#sTok293" value="Prs"/>
		<feat xlink:href="#sTok302" value="Art"/>
		<feat xlink:href="#sTok305" value="Art"/>
		<feat xlink:href="#sTok333" value="Int"/>
		<feat xlink:href="#sTok337" value="Art"/>
		<feat xlink:href="#sTok349" value="Prs"/>
		<feat xlink:href="#sTok369" value="Art"/>
		<feat xlink:href="#sTok379" value="Art"/>
		<feat xlink:href="#sTok454" value="Dem"/>
		<feat xlink:href="#sTok463" value="Art"/>
		<feat xlink:href="#sTok467" value="Art"/>
		<feat xlink:href="#sTok472" value="Rel"/>
		<feat xlink:href="#sTok476" value="Art"/>
		<feat xlink:href="#sTok502" value="Art"/>
		<feat xlink:href="#sTok515" value="Art"/>
		<feat xlink:href="#sTok521" value="Art"/>
		<feat xlink:href="#sTok531" value="Art"/>
		<feat xlink:href="#sTok534" value="Art"/>
		<feat xlink:href="#sTok576" value="Art"/>
		<feat xlink:href="#sTok587" value="Art"/>
		<feat xlink:href="#sTok590" value="Art"/>
		<feat xlink:href="#sTok615" value="Art"/>
		<feat xlink:href="#sTok623" value="Art"/>
		<feat xlink:href="#sTok626" value="Art"/>
		<feat xlink:href="#sTok634" value="Art"/>
		<feat xlink:href="#sTok637" value="Art"/>
		<feat xlink:href="#sTok679" value="Art"/>
		<feat xlink:href="#sTok689" value="Art"/>
		<feat xlink:href="#sTok719" value="Prs"/>
		<feat xlink:href="#sTok742" value="Art"/>
		<feat xlink:href="#sTok751" value="Prs"/>
		<feat xlink:href="#sTok752" value="Dem"/>
		<feat xlink:href="#sTok844" value="Art"/>
		<feat xlink:href="#sTok901" value="Prs"/>
		<feat xlink:href="#sTok904" value="Int"/>
		<feat xlink:href="#sTok910" value="Rel"/>
		<feat xlink:href="#sTok921" value="Art"/></featList></paula>