<?xml version="1.0" encoding="UTF-8" standalone="no"?>

<!DOCTYPE paula SYSTEM "paula_feat.dtd">
<paula version="1.0">

<header paula_id="tei.GUM.GUM_news_sensitive_p"/>

<featList xmlns:xlink="http://www.w3.org/1999/xlink" type="p" xml:base="tei.GUM.GUM_news_sensitive.pSeg.xml">
<feat xlink:href="#p_8" value="p"/><!-- Friday...2008 -->
<feat xlink:href="#p_14" value="p"/><!-- A.... -->
<feat xlink:href="#p_36" value="p"/><!-- The.... -->
<feat xlink:href="#p_59" value="p"/><!-- The.... -->
<feat xlink:href="#p_119" value="p"/><!-- The.... -->
<feat xlink:href="#p_170" value="p"/><!-- Protection.... -->
<feat xlink:href="#p_231" value="p"/><!-- Environment.... -->
<feat xlink:href="#p_260" value="p"/><!-- &quot;.... -->
<feat xlink:href="#p_292" value="p"/><!-- Environment.... -->
<feat xlink:href="#p_308" value="p"/><!-- &quot;.... -->
<feat xlink:href="#p_337" value="p"/><!-- Paul.... -->
<feat xlink:href="#p_364" value="p"/><!-- Dewar.... -->
<feat xlink:href="#p_417" value="p"/><!-- &quot;.... -->
<feat xlink:href="#p_447" value="p"/><!-- The.... -->
<feat xlink:href="#p_457" value="p"/><!-- In.... -->
<feat xlink:href="#p_485" value="p"/><!-- In.... -->
<feat xlink:href="#p_526" value="p"/><!-- &quot;...2008 -->
<feat xlink:href="#p_543" value="p"/><!-- &quot;...2008 -->
<feat xlink:href="#p_563" value="p"/><!-- &quot;...2008 -->
<feat xlink:href="#p_580" value="p"/><!-- Peter...2008 -->
<feat xlink:href="#p_600" value="p"/><!-- Categories...Archived -->
</featList>
</paula>
